mcp_streamablehttp_client/__init__.py
mcp_streamablehttp_client/cli.py
mcp_streamablehttp_client/config.py
mcp_streamablehttp_client/oauth.py
mcp_streamablehttp_client/proxy.py
mcp_streamablehttp_client/py.typed
mcp_streamablehttp_client-0.2.0.dist-info/METADATA
mcp_streamablehttp_client-0.2.0.dist-info/WHEEL
mcp_streamablehttp_client-0.2.0.dist-info/entry_points.txt
mcp_streamablehttp_client-0.2.0.dist-info/top_level.txt
mcp_streamablehttp_client-0.2.0.dist-info/RECORD
