Metadata-Version: 2.4
Name: mcp-streamablehttp-client
Version: 0.2.0
Summary: Streamable HTTP to stdio proxy client for MCP servers with OAuth support
Author: Andreas Trawoeger
License-Expression: Apache-2.0
Project-URL: Homepage, https://github.com/atrawog/mcp-oauth-gateway/tree/main/mcp-streamablehttp-client
Project-URL: Repository, https://github.com/atrawog/mcp-oauth-gateway/tree/main/mcp-streamablehttp-client
Project-URL: Issues, https://github.com/atrawog/mcp-oauth-gateway/issues
Project-URL: Documentation, https://atrawog.github.io/mcp-oauth-gateway
Keywords: mcp,proxy,oauth,stdio,streamable-http,client
Classifier: Development Status :: 4 - Beta
Classifier: Intended Audience :: Developers
Classifier: Programming Language :: Python :: 3
Classifier: Programming Language :: Python :: 3.10
Classifier: Programming Language :: Python :: 3.11
Classifier: Programming Language :: Python :: 3.12
Requires-Python: >=3.10
Requires-Dist: httpx>=0.24.0
Requires-Dist: python-dotenv>=1.0.0
Requires-Dist: click>=8.0.0
Requires-Dist: pydantic>=2.0.0
Requires-Dist: pydantic-settings>=2.0.0
Requires-Dist: anyio>=3.0.0
Requires-Dist: rich>=13.0.0
Requires-Dist: authlib>=1.3.0
Requires-Dist: mcp>=1.0.0
